cool_cache/__init__.py
cool_cache/settings.json
cool_cache/__dependencies__/__init__.py
cool_cache/__dependencies__/update_dependencies
cool_cache/__dependencies__/update_dependencies.ps1
cool_cache/__dependencies__/__pycache__/__init__.cpython-312.pyc
cool_cache/__dependencies__/__pycache__/__init__.cpython-38.pyc
cool_cache/__dependencies__/__sources__/file_system_py/.gitignore
cool_cache/__dependencies__/__sources__/file_system_py/.gitrepo
cool_cache/__dependencies__/__sources__/file_system_py/README.md
cool_cache/__dependencies__/__sources__/file_system_py/poetry.lock
cool_cache/__dependencies__/__sources__/file_system_py/pyproject.toml
cool_cache/__dependencies__/__sources__/file_system_py/commands/pip
cool_cache/__dependencies__/__sources__/file_system_py/commands/shell
cool_cache/__dependencies__/__sources__/file_system_py/commands/start
cool_cache/__dependencies__/__sources__/file_system_py/commands/subrepo
cool_cache/__dependencies__/__sources__/file_system_py/commands/project/clean
cool_cache/__dependencies__/__sources__/file_system_py/commands/project/commands
cool_cache/__dependencies__/__sources__/file_system_py/commands/project/local_install
cool_cache/__dependencies__/__sources__/file_system_py/commands/project/publish
cool_cache/__dependencies__/__sources__/file_system_py/commands/project/purge
cool_cache/__dependencies__/__sources__/file_system_py/documentation/fornix_framework.md
cool_cache/__dependencies__/__sources__/file_system_py/documentation/setup.md
cool_cache/__dependencies__/__sources__/file_system_py/documentation/images/cd_tutorial.gif
cool_cache/__dependencies__/__sources__/file_system_py/documentation/images/package_from_example.png
cool_cache/__dependencies__/__sources__/file_system_py/documentation/images/package_name.png
cool_cache/__dependencies__/__sources__/file_system_py/documentation/images/package_versions.png
cool_cache/__dependencies__/__sources__/file_system_py/logs/main.py.log
cool_cache/__dependencies__/__sources__/super_hash/main/super_hash.egg-info/PKG-INFO
cool_cache/__dependencies__/__sources__/super_hash/main/super_hash.egg-info/SOURCES.txt
cool_cache/__dependencies__/__sources__/super_hash/main/super_hash.egg-info/dependency_links.txt
cool_cache/__dependencies__/__sources__/super_hash/main/super_hash.egg-info/top_level.txt
cool_cache-0.4.0.dist-info/METADATA
cool_cache-0.4.0.dist-info/WHEEL
cool_cache-0.4.0.dist-info/top_level.txt
cool_cache-0.4.0.dist-info/RECORD
