Metadata-Version: 2.4
Name: cool_cache
Version: 0.4.0
Summary: Cache any function to disk
Home-page: https://github.com/jeff-hykin/cool_cache.git
Author: Jeff Hykin
Author-email: jeff.hykin@gmail.com
License: MIT
Requires-Python: >=3.6
Dynamic: author
Dynamic: author-email
Dynamic: description
Dynamic: description-content-type
Dynamic: home-page
Dynamic: license
Dynamic: requires-python
Dynamic: summary
